chaski/__init__.py
chaski/ca.py
chaski/logger.py
chaski/node.py
chaski/remote.py
chaski/streamer.py
chaski/scripts/__init__.py
chaski/scripts/certificate_authority.py
chaski/scripts/close_ports.py
chaski/scripts/remote_proxy.py
chaski/scripts/streamer_root.py
chaski/scripts/terminate_connections.py
chaski/utils/__init__.py
chaski/utils/auto.py
chaski/utils/certificate_authority.py
chaski/utils/debug.py
chaski/utils/viz.py
chaski_confluent-0.1a5.dist-info/LICENSE
chaski_confluent-0.1a5.dist-info/LICENSE.md
chaski_confluent-0.1a5.dist-info/METADATA
chaski_confluent-0.1a5.dist-info/WHEEL
chaski_confluent-0.1a5.dist-info/entry_points.txt
chaski_confluent-0.1a5.dist-info/top_level.txt
chaski_confluent-0.1a5.dist-info/RECORD
