Metadata-Version: 2.1
Name: chaski-confluent
Version: 0.1a5
Summary: Chaski Confluent
Author-email: Yeison Cardona <yencardonaal@unal.edu.co>
Maintainer-email: Yeison Cardona <yencardonaal@unal.edu.co>
License: BSD-2-Clause
Project-URL: Repository, https://github.com/dunderlab/python-chaski
Classifier: Development Status :: 3 - Alpha
Classifier: Environment :: Console
Classifier: Intended Audience :: Developers
Classifier: Intended Audience :: Science/Research
Classifier: License :: OSI Approved :: BSD License
Classifier: Natural Language :: English
Classifier: Operating System :: OS Independent
Classifier: Programming Language :: Python
Classifier: Programming Language :: Python :: 3.8
Classifier: Programming Language :: Python :: 3.9
Classifier: Programming Language :: Python :: 3.10
Classifier: Programming Language :: Python :: 3.11
Classifier: Programming Language :: Python :: 3.12
Classifier: Topic :: Software Development :: Libraries :: Python Modules
Requires-Python: >=3.8
License-File: LICENSE
License-File: LICENSE.md
Provides-Extra: dev
Requires-Dist: networkx; extra == "dev"
Requires-Dist: matplotlib; extra == "dev"
Requires-Dist: colorama; extra == "dev"
Provides-Extra: docs
Provides-Extra: security
Requires-Dist: cryptography; extra == "security"
